SoukTime/SoukTime.py
SoukTime/__init__.py
souktime-0.1.0.dist-info/METADATA
souktime-0.1.0.dist-info/WHEEL
souktime-0.1.0.dist-info/top_level.txt
souktime-0.1.0.dist-info/RECORD
