Metadata-Version: 2.4
Name: SoukTime
Version: 0.1.0
Requires-Dist: requests
